lovely-logger/__init__.py
lovely_logger/__init__.py
lovely_logger/__main__.py
lovely_logger-1.0.7.dist-info/LICENSE
lovely_logger-1.0.7.dist-info/METADATA
lovely_logger-1.0.7.dist-info/WHEEL
lovely_logger-1.0.7.dist-info/top_level.txt
lovely_logger-1.0.7.dist-info/RECORD
