Metadata-Version: 2.1
Name: lovely_logger
Version: 1.0.7
Summary: A logger library which builds on, combines, and simplifies various logging features of Python 3
Home-page: https://github.com/tier2tickets/lovely_logger
Author: Chris Wheeler
Author-email: grintor@gmail.com
License: MIT
Platform: UNKNOWN
Classifier: License :: OSI Approved :: GNU Lesser General Public License v2 or later (LGPLv2+)
Classifier: Programming Language :: Python :: 3
Classifier: Programming Language :: Python :: 3.6
Classifier: Programming Language :: Python :: 3.7
Classifier: Programming Language :: Python :: 3.8
Classifier: Programming Language :: Python :: 3.9
Classifier: Programming Language :: Python :: 3.10
License-File: LICENSE
